Ethnologue-0.0.9.data/data/data/etho.json/etho.json
etho/__init__.py
etho/pyetho.py
etho/data/etho.json
Ethnologue-0.0.9.dist-info/METADATA
Ethnologue-0.0.9.dist-info/WHEEL
Ethnologue-0.0.9.dist-info/top_level.txt
Ethnologue-0.0.9.dist-info/RECORD
