Metadata-Version: 2.1
Name: Ethnologue
Version: 0.0.9
Summary: Exploration of World Languages
Home-page: https://github.com/i18nsolutionspy/Ethnologue
Author: SathishKumar paramasivam Et al.
Author-email: i18nsolutionspy@gmail.com
Project-URL: Bug Tracker, https://github.com/i18nsolutionspy/Ethnologue/issues
Classifier: Programming Language :: Python :: 3
Classifier: License :: OSI Approved :: MIT License
Classifier: Operating System :: OS Independent
Requires-Python: >=3.6
